rubigram/__init__.py
rubigram/client.py
rubigram/dispatcher.py
rubigram/errors.py
rubigram/filters.py
rubigram/http_session.py
rubigram/enums/__init__.py
rubigram/enums/chat_action_type.py
rubigram/enums/chat_keypad_type.py
rubigram/enums/chat_type.py
rubigram/enums/enum.py
rubigram/enums/file_type.py
rubigram/enums/forwarded_from_type.py
rubigram/enums/handler_type.py
rubigram/enums/live_location_status.py
rubigram/enums/message_sender_type.py
rubigram/enums/metadata_type.py
rubigram/enums/parse_mode.py
rubigram/enums/payment_status_type.py
rubigram/enums/poll_status_type.py
rubigram/enums/update_endpoint_type.py
rubigram/enums/update_type.py
rubigram/enums/buttons/__init__.py
rubigram/enums/buttons/button_calendar_type.py
rubigram/enums/buttons/button_location_type.py
rubigram/enums/buttons/button_selection_get_type.py
rubigram/enums/buttons/button_selection_search_type.py
rubigram/enums/buttons/button_selection_type.py
rubigram/enums/buttons/button_textbox_type_keypad.py
rubigram/enums/buttons/button_textbox_type_line.py
rubigram/enums/buttons/button_type.py
rubigram/handlers/__init__.py
rubigram/handlers/handler.py
rubigram/methods/__init__.py
rubigram/methods/chats/__init__.py
rubigram/methods/chats/ban_chat_member.py
rubigram/methods/chats/get_chat.py
rubigram/methods/chats/get_chat_member.py
rubigram/methods/chats/unban_chat_member.py
rubigram/methods/decorators/__init__.py
rubigram/methods/decorators/on_deleted_message.py
rubigram/methods/decorators/on_inline_message.py
rubigram/methods/decorators/on_message.py
rubigram/methods/decorators/on_start.py
rubigram/methods/decorators/on_started_bot.py
rubigram/methods/decorators/on_stop.py
rubigram/methods/decorators/on_stopped_bot.py
rubigram/methods/decorators/on_update_message.py
rubigram/methods/files/__init__.py
rubigram/methods/files/get_file.py
rubigram/methods/files/request_send_file.py
rubigram/methods/files/send_document.py
rubigram/methods/files/send_file.py
rubigram/methods/files/send_gif.py
rubigramclient-1.7.23.dist-info/licenses/LICENSE
rubigramclient-1.7.23.dist-info/METADATA
rubigramclient-1.7.23.dist-info/WHEEL
rubigramclient-1.7.23.dist-info/top_level.txt
rubigramclient-1.7.23.dist-info/RECORD
