Metadata-Version: 2.4
Name: RubigramClient
Version: 1.7.23
Summary: A simple and flexible Python library for building advanced Rubika bots with powerful message handling, inline buttons, and custom filters.
Author-email: Javad <MrJavad.Email@gmail.com>
License: MIT License
Project-URL: GitHub, https://github.com/DevJavad/rubigram
Classifier: Programming Language :: Python :: 3
Classifier: License :: OSI Approved :: MIT License
Classifier: Operating System :: OS Independent
Requires-Python: >=3.4
License-File: LICENSE
Requires-Dist: aiohttp
Requires-Dist: aiofiles
Requires-Dist: aiocache
Requires-Dist: markdownify
Dynamic: license-file
